fsl/version.py
fsl/data/__init__.py
fsl/data/atlases.py
fsl/data/bitmap.py
fsl/data/cifti.py
fsl/data/constants.py
fsl/data/dicom.py
fsl/data/dtifit.py
fsl/data/featanalysis.py
fsl/data/featdesign.py
fsl/data/featimage.py
fsl/data/fixlabels.py
fsl/data/freesurfer.py
fsl/data/gifti.py
fsl/data/image.py
fsl/data/imagewrapper.py
fsl/data/melodicanalysis.py
fsl/data/melodicimage.py
fsl/data/mesh.py
fsl/data/mghimage.py
fsl/data/utils.py
fsl/data/vest.py
fsl/data/volumelabels.py
fsl/data/vtk.py
fsl/scripts/Text2Vest.py
fsl/scripts/Vest2Text.py
fsl/scripts/atlasq.py
fsl/scripts/fsl_abspath.py
fsl/scripts/fsl_apply_x5.py
fsl/scripts/fsl_convert_x5.py
fsl/scripts/fsl_ents.py
fsl/scripts/imcp.py
fsl/scripts/imglob.py
fsl/scripts/imln.py
fsl/scripts/immv.py
fsl/scripts/imrm.py
fsl/scripts/imtest.py
fsl/scripts/remove_ext.py
fsl/scripts/resample_image.py
fsl/tests/__init__.py
fsl/tests/test_assertions.py
fsl/tests/test_atlases.py
fsl/tests/test_atlases_query.py
fsl/tests/test_bids.py
fsl/tests/test_bitmap.py
fsl/tests/test_cache.py
fsl/tests/test_cifti.py
fsl/tests/test_deprecated.py
fsl/tests/test_dicom.py
fsl/tests/test_dtifit.py
fsl/tests/test_ensure.py
fsl/tests/test_featanalysis.py
fsl/tests/test_featdesign.py
fsl/tests/test_featimage.py
fsl/tests/test_fixlabels.py
fsl/tests/test_freesurfer.py
fsl/tests/test_fsl_data_utils.py
fsl/tests/test_fsl_utils_path.py
fsl/tests/test_fslsub.py
fsl/tests/test_gifti.py
fsl/tests/test_idle.py
fsl/tests/test_image.py
fsl/tests/test_image_data_access.py
fsl/tests/test_image_resample.py
fsl/tests/test_image_roi.py
fsl/tests/test_immv_imcp.py
fsl/tests/test_importall.py
fsl/tests/test_melodicanalysis.py
fsl/tests/test_melodicimage.py
fsl/tests/test_memoize.py
fsl/tests/test_mesh.py
fsl/tests/test_meta.py
fsl/tests/test_mghimage.py
fsl/tests/test_naninfrange.py
fsl/tests/test_notifier.py
fsl/tests/test_parse_data.py
fsl/tests/test_platform.py
fsl/tests/test_run.py
fsl/tests/test_settings.py
fsl/tests/test_tempdir.py
fslpy-3.26.0.dist-info/licenses/LICENSE
fslpy-3.26.0.dist-info/METADATA
fslpy-3.26.0.dist-info/WHEEL
fslpy-3.26.0.dist-info/entry_points.txt
fslpy-3.26.0.dist-info/top_level.txt
fslpy-3.26.0.dist-info/RECORD
