Metadata-Version: 2.4
Name: fslpy
Version: 3.26.0
Summary: FSL Python library
Author-email: Paul McCarthy <pauldmccarthy@gmail.com>
License: Apache License Version 2.0
Project-URL: Repository, https://git.fmrib.ox.ac.uk/fsl/fslpy/
Project-URL: Documentation, https://open.win.ox.ac.uk/pages/fsl/fslpy/
Classifier: Development Status :: 3 - Alpha
Classifier: Intended Audience :: Developers
Classifier: License :: OSI Approved :: Apache Software License
Classifier: Programming Language :: Python :: 3.10
Classifier: Programming Language :: Python :: 3.11
Classifier: Programming Language :: Python :: 3.12
Classifier: Programming Language :: Python :: 3.13
Classifier: Topic :: Software Development :: Libraries :: Python Modules
Requires-Python: >=3.8
License-File: LICENSE
Requires-Dist: dill
Requires-Dist: h5py>=2.9
Requires-Dist: nibabel>=2.4
Requires-Dist: numpy>=1
Requires-Dist: scipy>=0.18
Provides-Extra: extra
Requires-Dist: indexed_gzip>=0.7; extra == "extra"
Requires-Dist: wxpython>=4; extra == "extra"
Requires-Dist: trimesh>=2.37.29; extra == "extra"
Requires-Dist: rtree>=0.8.3; extra == "extra"
Requires-Dist: Pillow>=3.2.0; extra == "extra"
Requires-Dist: pyzstd; extra == "extra"
Provides-Extra: doc
Requires-Dist: sphinx; extra == "doc"
Requires-Dist: sphinx_rtd_theme; extra == "doc"
Provides-Extra: test
Requires-Dist: pytest; extra == "test"
Requires-Dist: coverage; extra == "test"
Requires-Dist: pytest-cov; extra == "test"
Requires-Dist: tomli; python_version < "3.11" and extra == "test"
Provides-Extra: style
Requires-Dist: pylint; extra == "style"
Requires-Dist: flake8; extra == "style"
Dynamic: license-file
